{
  "vehicles": [
    {
      "id": 1,
      "name": "Chevrolet Cruze",
      "image": "https://mwendoafrica.com/wp-content/uploads/2023/01/CARS-PNG-07-350x350.png",
      "price": "1000",
      "fuel": "Petrol",
      "engine_capacity": "1999 cc",
      "seats": "5 seats",
      "Transmission": "Automatic",
      "air_bags": "4",
      "type": "car",
      "rating": "4.5"
    },
    {
      "id": 2,
      "name": "Honda Jazz",
      "image": "https://mwendoafrica.com/wp-content/uploads/2023/01/Jazz-350x350.jpg",
      "price": "1000",
      "fuel": "Petrol",
      "engine_capacity": "1300 ccm",
      "seats": "4 seats",
      "Transmission": "Manual",
      "air_bags": "2",
      "type": "car",
      "rating": "4"
    },
    {
      "id": 3,
      "name": "Lexus SUV",
      "image": "https://mwendoafrica.com/wp-content/uploads/2023/01/CARS-PNG-05-350x350.png",
      "price": "1900",
      "fuel": "Diesel",
      "engine_capacity": "2800 cc",
      "seats": "5 seats",
      "Transmission": "Manual",
      "air_bags": "4",
      "type": "SUVs",
      "rating": "4.5"
    },
    {
      "id": 4,
      "name": "Subaru Forester",
      "image": "https://mwendoafrica.com/wp-content/uploads/2023/01/SUBARU-350x350.jpg",
      "price": "1600",
      "fuel": "Petrol",
      "engine_capacity": "2800 cc",
      "seats": "5 seats",
      "Transmission": "Automatic",
      "air_bags": "4",
      "type": "SUVs",
      "rating": "4"
    },
    {
      "id": 5,
      "name": "Setra Luxry Bus",
      "image": "https://mwendoafrica.com/wp-content/uploads/2018/08/CARS-PNG-02-350x350.png",
      "price": "5200",
      "fuel": "Diesel",
      "engine_capacity": "3800 cc",
      "seats": "32 seats",
      "Transmission": "Manual",
      "air_bags": "2",
      "type": "bus",
      "rating": "4.5"
    },
    {
      "id": 6,
      "name": "Hilux Double Cab",
      "image": "https://mwendoafrica.com/wp-content/uploads/2023/01/CARS-PNG-11-350x350.png",
      "price": "1200",
      "fuel": "Diesel",
      "engine_capacity": "2800 cc",
      "seats": "2 seats",
      "Transmission": "Manual",
      "air_bags": "2",
      "type": "pick_up",
      "rating": "4"
    },
    {
      "id": 7,
      "name": "Hyundai Tucson",
      "image": "https://mwendoafrica.com/wp-content/uploads/2023/01/CARS-PNG-08-350x350.png",
      "price": "1300",
      "fuel": "Petrol",
      "engine_capacity": "1600 cc",
      "seats": "5 seats",
      "Transmission": "Automatic",
      "air_bags": "4",
      "type": "car",
      "rating": "4"
    },
    {
      "id": 8,
      "name": "Toyota Fortuner",
      "image": "https://mwendoafrica.com/wp-content/uploads/2023/01/fortuner-350x350.jpg",
      "price": "1700",
      "fuel": "Petrol",
      "engine_capacity": "2700 cc",
      "seats": "7 seats",
      "Transmission": "Automatic",
      "air_bags": "4",
      "type": "SUVs",
      "rating": "4.5"
    },
    {
      "id": 9,
      "name": "Fortuner GD6",
      "image": "https://mwendoafrica.com/wp-content/uploads/2023/03/GD6-350x350.jpg",
      "price": "1990",
      "fuel": "Petrol",
      "engine_capacity": "2500 cc",
      "seats": "5 seats",
      "Transmission": "Manual",
      "air_bags": "4",
      "type": "SUVs",
      "rating": "4.5"
    },
    {
      "id": 10,
      "name": "Toyota Land Cruiser VX",
      "image": "https://mwendoafrica.com/wp-content/uploads/2023/03/LAND-CRUISE-VX-350x350.jpg",
      "price": "2500",
      "fuel": "Diesel",
      "engine_capacity": "4461 cc",
      "seats": "7 seats",
      "Transmission": "Automatic",
      "air_bags": "4",
      "type": "SUVs",
      "rating": "4"
    },
    {
      "id": 11,
      "name": "Fort Ranger",
      "image": "https://mwendoafrica.com/wp-content/uploads/2018/08/CARS-PNG-12-350x350.png",
      "price": "1400",
      "fuel": "Diesel",
      "engine_capacity": "2800 cc",
      "seats": "4 seats",
      "Transmission": "Automatic",
      "air_bags": "2",
      "type": "pick_up",
      "rating": "4.5"
    },
    {
      "id": 12,
      "name": "Mercedes Benze Class",
      "image": "https://mwendoafrica.com/wp-content/uploads/2023/03/E-CLASS-350x350.jpg",
      "price": "1890",
      "fuel": "Petrol",
      "engine_capacity": "2999 cc",
      "seats": "5 seats",
      "Transmission": "Automatic",
      "air_bags": "4",
      "type": "car",
      "rating": "4.5"
    },
    {
      "id": 13,
      "name": "Luxury Mini Bus",
      "image": "https://mwendoafrica.com/wp-content/uploads/2023/01/CARS-PNG-01-350x350.png",
      "price": "1200",
      "fuel": "Diesel",
      "engine_capacity": "2800 cc",
      "seats": "9 seats",
      "Transmission": "Manual",
      "air_bags": "2",
      "type": "bus",
      "rating": "4.5"
    },
    {
      "id": 14,
      "name": "Nissan Almera",
      "image": "https://mwendoafrica.com/wp-content/uploads/2018/08/CARS-PNG-06-350x350.png",
      "price": "1200",
      "fuel": "Petrol",
      "engine_capacity": "2500 cc",
      "seats": "5 seats",
      "Transmission": "Manual",
      "air_bags": "3",
      "type": "car",
      "rating": "4"
    },
    {
      "id": 15,
      "name": "Toyota Coaster",
      "image": "https://mwendoafrica.com/wp-content/uploads/2018/08/CARS-PNG-04-350x350.png",
      "price": "3200",
      "fuel": "Diesel",
      "engine_capacity": "3800 cc",
      "seats": "32 seats",
      "Transmission": "Manual",
      "air_bags": "2",
      "type": "bus",
      "rating": "4"
    },
    {
      "id": 16,
      "name": "Toyota Corolla",
      "image": "https://mwendoafrica.com/wp-content/uploads/2023/03/MWENDO-AFRICA-CAR-350x350.jpg",
      "price": "1500",
      "fuel": "Petrol",
      "engine_capacity": "1999 cc",
      "seats": "5 seats",
      "Transmission": "Manual",
      "air_bags": "4",
      "type": "car",
      "rating": "4.5"
    },
    {
      "id": 17,
      "name": "Toyota Hilux GD6",
      "image": "https://mwendoafrica.com/wp-content/uploads/2023/03/HILUX-GD6-350x350.jpg",
      "price": "1600",
      "fuel": "Diesel",
      "engine_capacity": "2800 cc",
      "seats": "4 seats",
      "Transmission": "Manual",
      "air_bags": "2",
      "type": "pick_up",
      "rating": "4"
    },
    {
      "id": 18,
      "name": "Mercedes Benz GLS",
      "image": "https://mwendoafrica.com/wp-content/uploads/2018/08/CARS-PNG-09-350x350.png",
      "price": "1500",
      "fuel": "Petrol",
      "engine_capacity": "2800 cc",
      "seats": "5 seats",
      "Transmission": "Automatic",
      "air_bags": "4",
      "type": "SUVs",
      "rating": "4.5"
    },
    {
      "id": 19,
      "name": "Quantam",
      "image": "https://mwendoafrica.com/wp-content/uploads/2018/08/CARS-PNG-10-350x350.png",
      "price": "1200",
      "fuel": "Diesel",
      "engine_capacity": "3800 cc",
      "seats": "9 seats",
      "Transmission": "Manual",
      "air_bags": "2",
      "type": "bus",
      "rating": "4"
    }
  ],
  "cart": [
    {
      "id": 1,
      "name": "Chevrolet Cruze",
      "image": "https://mwendoafrica.com/wp-content/uploads/2023/01/CARS-PNG-07-350x350.png",
      "price": "1000",
      "fuel": "Petrol",
      "engine_capacity": "1999 cc",
      "seats": "5 seats",
      "Transmission": "Automatic",
      "air_bags": "4",
      "type": "car",
      "rating": "4.5"
    }
  ]
}
